moonwiki/__init__.py
moonwiki-2023.7.11.5.dist-info/METADATA
moonwiki-2023.7.11.5.dist-info/WHEEL
moonwiki-2023.7.11.5.dist-info/top_level.txt
moonwiki-2023.7.11.5.dist-info/RECORD
