Metadata-Version: 2.1
Name: moonwiki
Version: 2023.7.11.5
Summary: moonwiki is a wiki application made with Python
Home-page: https://github.com/RixTheTyrunt/moonwiki
Author: RixTheTyrunt
Author-email: rixthetyrunt@gmail.com
Requires-Python: >=3
